spyglasses/__init__.py
spyglasses/client.py
spyglasses/configuration.py
spyglasses/exceptions.py
spyglasses/types.py
spyglasses/middleware/__init__.py
spyglasses/middleware/asgi.py
spyglasses/middleware/base.py
spyglasses/middleware/django.py
spyglasses/middleware/fastapi.py
spyglasses/middleware/flask.py
spyglasses/middleware/wsgi.py
spyglasses-1.0.3.dist-info/METADATA
spyglasses-1.0.3.dist-info/WHEEL
spyglasses-1.0.3.dist-info/licenses/LICENSE
spyglasses-1.0.3.dist-info/RECORD
