Metadata-Version: 2.4
Name: spyglasses
Version: 1.0.3
Summary: AI Agent Detection and Management for Python web applications
Project-URL: Homepage, https://spyglasses.io
Project-URL: Documentation, https://www.spyglasses.io/docs/platforms/python
Project-URL: Repository, https://github.com/orchestra-code/spyglasses-python
Project-URL: Changelog, https://github.com/orchestra-code/spyglasses-python/blob/main/CHANGELOG.md
Project-URL: Bug Tracker, https://github.com/orchestra-code/spyglasses-python/issues
Author-email: Spyglasses <support@spyglasses.io>
License: MIT
License-File: LICENSE
Keywords: agent,ai,bot,crawler,detection,django,fastapi,flask,middleware,security,web
Classifier: Development Status :: 4 - Beta
Classifier: Environment :: Web Environment
Classifier: Framework :: Django
Classifier: Framework :: FastAPI
Classifier: Framework :: Flask
Classifier: Intended Audience :: Developers
Classifier: License :: OSI Approved :: MIT License
Classifier: Operating System :: OS Independent
Classifier: Programming Language :: Python
Classifier: Programming Language :: Python :: 3
Classifier: Programming Language :: Python :: 3.8
Classifier: Programming Language :: Python :: 3.9
Classifier: Programming Language :: Python :: 3.10
Classifier: Programming Language :: Python :: 3.11
Classifier: Programming Language :: Python :: 3.12
Classifier: Topic :: Internet :: WWW/HTTP
Classifier: Topic :: Internet :: WWW/HTTP :: WSGI
Classifier: Topic :: Internet :: WWW/HTTP :: WSGI :: Middleware
Classifier: Topic :: Security
Classifier: Topic :: Software Development :: Libraries :: Python Modules
Requires-Python: >=3.8
Requires-Dist: requests>=2.25.0
Requires-Dist: typing-extensions>=4.0.0; python_version < '3.10'
Provides-Extra: dev
Requires-Dist: black>=22.0; extra == 'dev'
Requires-Dist: httpx>=0.24.0; extra == 'dev'
Requires-Dist: mypy>=1.0; extra == 'dev'
Requires-Dist: pytest-asyncio>=0.21.0; extra == 'dev'
Requires-Dist: pytest-cov>=4.0; extra == 'dev'
Requires-Dist: pytest>=7.0; extra == 'dev'
Requires-Dist: ruff>=0.1.0; extra == 'dev'
Requires-Dist: types-requests; extra == 'dev'
Provides-Extra: django
Requires-Dist: django>=3.2; extra == 'django'
Provides-Extra: fastapi
Requires-Dist: fastapi>=0.68.0; extra == 'fastapi'
Requires-Dist: starlette>=0.14.2; extra == 'fastapi'
Provides-Extra: flask
Requires-Dist: flask>=2.0; extra == 'flask'
